<annotation>
	<folder>JPEGImages</folder>
	<filename>000934.jpg</filename>
	<path>C:\Users\Admin\Desktop\xia\DAGM2007_VOC\train\JPEGImages\000934.jpg</path>
	<source>
		<database>Unknown</database>
	</source>
	<size>
		<width>512</width>
		<height>512</height>
		<depth>1</depth>
	</size>
	<segmented>0</segmented>
	<object>
		<name>Class10</name>
		<pose>Unspecified</pose>
		<truncated>0</truncated>
		<difficult>0</difficult>
		<bndbox>
			<xmin>272</xmin>
			<ymin>387</ymin>
			<xmax>346</xmax>
			<ymax>433</ymax>
		</bndbox>
	</object>
</annotation>